LICENSE
MANIFEST.in
README.md
setup.cfg
setup.py
versioneer.py
cuda/bindings.cu
cuda/experimental_kernels.h
cuda/leaky_kernels.h
cuda/lif_kernels.h
sinabs/exodus/__init__.py
sinabs/exodus/_version.py
sinabs/exodus/conversion.py
sinabs/exodus/leaky.py
sinabs/exodus/spike.py
sinabs/exodus/layers/__init__.py
sinabs/exodus/layers/exp_leak.py
sinabs/exodus/layers/iaf.py
sinabs/exodus/layers/lif.py
sinabs_exodus.egg-info/PKG-INFO
sinabs_exodus.egg-info/SOURCES.txt
sinabs_exodus.egg-info/dependency_links.txt
sinabs_exodus.egg-info/requires.txt
sinabs_exodus.egg-info/top_level.txt
tests/test_conversion.py
tests/test_exp_leak.py
tests/test_iaf.py
tests/test_leak_functions.py
tests/test_lif.py
tests/test_spike_functions.py