Metadata-Version: 2.1
Name: sinabs-exodus
Version: 2.0.0
Summary: Efficient training and inference on GPU for sinabs spiking neural network simulator.
Author: SynSense (formerly AiCTX)
Author-email: sinabs@synsense.ai
License: Apache 2.0
Project-URL: Source code, https://github.com/synsense/sinabs-exodus
Project-URL: Documentation, https://readthedocs.org/projects/sinabs/
Keywords: spiking neural networks,machine learning,SNN,GPU
Classifier: Development Status :: 4 - Beta
Classifier: Environment :: Console
Classifier: Intended Audience :: Science/Research
Classifier: Intended Audience :: Developers
Classifier: License :: OSI Approved :: Apache Software License
Classifier: Programming Language :: Python :: 3
License-File: LICENSE
